[
    {
        "title": "JELURIDA MADE THE 4YFN AWARD FINALS!!!!!",
        "ups": 54
    },
    {
        "title": "Upvote Ardor for new exchange!",
        "ups": 53
    },
    {
        "title": "Gonna be a long haul, better meme it up",
        "ups": 48
    },
    {
        "title": "3 hour Social Media Blast THIS TUESDAY February 27 - check for timezones and hashtags and spread the news.",
        "ups": 35
    },
    {
        "title": "Why Wait for Bitcoin's Lightning Network?",
        "ups": 31
    },
    {
        "title": "JP Morgan Chase Managing Director becomes a senior adviser to the Triffic ICO",
        "ups": 30
    },
    {
        "title": "Seems like successful fundraising made some buzz in crypto media this week (+150% in Social Volume according to Solume.io).",
        "ups": 29
    },
    {
        "title": "This is how Ardor will be able to hit the mainstream and actually change the world...",
        "ups": 27
    },
    {
        "title": "Upcoming Event: Ardor (ARDR), Nxt (NXT) Conference MWC Barcelona - March 1, 2018",
        "ups": 25
    },
    {
        "title": "4yfn today, hold the line!",
        "ups": 22
    },
    {
        "title": "Poloniex and Circle team together as of today .. Maybe we can start pushing that they fix ardor again ?!",
        "ups": 22
    },
    {
        "title": "Q&amp;A with Lior!",
        "ups": 21
    },
    {
        "title": "3 hr TWEET BLAST NOW! Use all 3 standard hashtags: #Ardor4YFN #Ardor #MWC2018 ! Ends at 11am EST/ 8am PST/ 5pm CET.",
        "ups": 18
    },
    {
        "title": "The Crypto Report Card...",
        "ups": 13
    },
    {
        "title": "Help Ardor, help yourself! -&gt; Tweet a unique post with the hashtags #Ardor4YFN #Ardor #MWC2018 ! Ends at 11am EST/ 8am PST/ 5pm CET.",
        "ups": 12
    },
    {
        "title": "I've built a multi-coin OLED ticker. As a great believer in Ardor, I'm listing it where it should stay: between the top 10 coins.",
        "ups": 14
    },
    {
        "title": "LELE Airdrop for IGNIS on ARDR",
        "ups": 11
    },
    {
        "title": "Ardor: There Is a Reason Behind Lack of Marketing Efforts",
        "ups": 12
    },
    {
        "title": "Upcoming Event: Ardor (ARDR) Ardor/Ignis Workshop - March 20, 2018",
        "ups": 11
    },
    {
        "title": "The Ardor Diet",
        "ups": 8
    },
    {
        "title": "help please, for Ardor",
        "ups": 8
    },
    {
        "title": "Marketing: How ARK are prioritizing their marketing message",
        "ups": 7
    },
    {
        "title": "OUR BINANCE LISTING &amp; VOTE, WHERE ARE WE ON THE LIST ????????",
        "ups": 8
    },
    {
        "title": "Nxter News \u2013 February 2018 (IV): Logic Will Get You From A to Z; Imagination Will Get You Everywhere",
        "ups": 5
    },
    {
        "title": "ARDOR, LETS GET THE MARKET",
        "ups": 6
    }
]