[
    {
        "title": "Update On KuCoin Bonus And Gas Reward",
        "ups": 47
    },
    {
        "title": "Please take a look Kucoin developers !!",
        "ups": 42
    },
    {
        "title": "Change of attitude? KuCoin is communicating.",
        "ups": 41
    },
    {
        "title": "Official Statement About Funds",
        "ups": 34
    },
    {
        "title": "Funds Have Been Recovered",
        "ups": 28
    },
    {
        "title": "Important Notice About System Update",
        "ups": 28
    },
    {
        "title": "KCS Bonus seems to have stabilised",
        "ups": 30
    },
    {
        "title": "TEARS OF JOY. MY ASSETS ARE BACK. THANKS KUCOIN. I'll name my fiisrt boy after Kucoin.",
        "ups": 23
    },
    {
        "title": "KCS generated NEO generating GAS dividends consistently in the past week",
        "ups": 22
    },
    {
        "title": "[Guide] Step by Step: KuCoin Exchange",
        "ups": 21
    },
    {
        "title": "Kucoin Daily Volume Falls Below 50 Million?!? -",
        "ups": 20
    },
    {
        "title": "Moonshot Week 5: Own Where You Trade, KuCoin Shares (KCS)...KuCoin Get Your SH*T TOGETHER",
        "ups": 17
    },
    {
        "title": "List all top 25 crypto on the exchange!",
        "ups": 19
    },
    {
        "title": "Just received a bunch of trading competition payouts",
        "ups": 17
    },
    {
        "title": "Can't withdraw from the Exchange: Over 24 Hours",
        "ups": 16
    },
    {
        "title": "Stop Limit",
        "ups": 15
    },
    {
        "title": "Get all your order history as CSV file",
        "ups": 13
    },
    {
        "title": "Trading competition reward",
        "ups": 15
    },
    {
        "title": "Kucoin distributes how much fees after March 2018?",
        "ups": 13
    },
    {
        "title": "DAT Competition Has Now Concluded",
        "ups": 17
    },
    {
        "title": "JHust received competition prizes: DAT &amp; HPB https://ibb.co/hvHnOH https://ibb.co/f6U1iH https://ibb.co/cfhbHc",
        "ups": 14
    },
    {
        "title": "Jibrel Network (JNT) Gets Listed On KuCoin!",
        "ups": 15
    },
    {
        "title": "Not getting withdrawal emails?",
        "ups": 15
    },
    {
        "title": "Email System Update",
        "ups": 12
    },
    {
        "title": "Does anyone know if Kucoin will continue to offer the .50 profit share or are the planning to drop it.",
        "ups": 13
    }
]