[
    {
        "title": "Request Network Team AMA 02/03/2018.",
        "ups": 233
    },
    {
        "title": "Mainnet audit branch created...\ud83e\udd14",
        "ups": 223
    },
    {
        "title": "The Potential of Request Network ($REQ) and a Beginner Introduction",
        "ups": 210
    },
    {
        "title": "Request Network | 6 use cases for the Request Network",
        "ups": 177
    },
    {
        "title": "Request Network Review: Payment Solution of the Future",
        "ups": 170
    },
    {
        "title": "Upcoming Event: Request Network (REQ) Listing on Koinex - February 23, 2018",
        "ups": 152
    },
    {
        "title": "REQ is the runner up for BBR's upcoming vote. There's one week left to turn things around!",
        "ups": 146
    },
    {
        "title": "This is why we need Request Network",
        "ups": 148
    },
    {
        "title": "VOTE for REQ - currently 2nd place!",
        "ups": 128
    },
    {
        "title": "Request Network - Fundamental Analysis",
        "ups": 114
    },
    {
        "title": "REQ Going Bonkers on Binance",
        "ups": 115
    },
    {
        "title": "Let's ease it up a bit with the r/ cryptocurrency shilling guys.",
        "ups": 111
    },
    {
        "title": "RequestNetwork is now available on Koinex, India's largest crypto exchange.",
        "ups": 112
    },
    {
        "title": "Chango -- An App Created by Tech Giant Elunic for Simplifying Financial Transactions Between Friends Using REQ",
        "ups": 108
    },
    {
        "title": "General trend is up in mentions and tags used on social media are very \"interesting\" for RequestNetwork . Mentions, tags and themes at a glance for REQ .",
        "ups": 89
    },
    {
        "title": "Double Bottom + RSI oversold = Buy opportunity?",
        "ups": 86
    },
    {
        "title": "REQ is a Utility Token",
        "ups": 82
    },
    {
        "title": "BitPay Banning Explicit Goods &amp; Services -- REQ Running Out of Competitors. I'm So Bullish.",
        "ups": 81
    },
    {
        "title": "Vote for Black Block Research's next research report",
        "ups": 69
    },
    {
        "title": "The cryptotrader's favourite REQ use case",
        "ups": 71
    },
    {
        "title": "The Year Of Request Network",
        "ups": 67
    },
    {
        "title": "Trade Recommendation: Request Network",
        "ups": 64
    },
    {
        "title": "REQ really climbing the charts today. 82 on CMC",
        "ups": 60
    },
    {
        "title": "REQ volume",
        "ups": 62
    },
    {
        "title": "Kyber whitelist - Trading REQ",
        "ups": 57
    }
]