[
    {
        "title": "How much LBC is held by LBRY?",
        "ups": 12
    },
    {
        "title": "Where's LBRY headed in 2018? Find out here!",
        "ups": 13
    },
    {
        "title": "Meet Lee Brian, the LBRYian.",
        "ups": 10
    },
    {
        "title": "LBC/FIAT Gateway is coming.",
        "ups": 10
    },
    {
        "title": "LBRY v0.20 is live with SMS verification, night mode, and more!",
        "ups": 8
    },
    {
        "title": "LBRY Crypto review because we're living on the blockchain! #BL1",
        "ups": 7
    },
    {
        "title": "What features do you want to see added?",
        "ups": 7
    },
    {
        "title": "Upcoming Event: LBRY Credits (LBC) Whitepaper - March 1, 2018",
        "ups": 7
    },
    {
        "title": "Tate Modern - Smith",
        "ups": 8
    },
    {
        "title": "Streaming is shit",
        "ups": 6
    },
    {
        "title": "How I feel when I tell friends SMS verification is up w/ new LBRYCast Rewards",
        "ups": 7
    },
    {
        "title": "Best pools to mine at?",
        "ups": 4
    },
    {
        "title": "Contest Winners (January 2018)",
        "ups": 5
    },
    {
        "title": "Upcoming Event: LBRY Credits (LBC) Blockchain Conference - February 16, 2018",
        "ups": 5
    },
    {
        "title": "LBRY Network Gif",
        "ups": 4
    },
    {
        "title": "Read \"Top 10 Anticipated Features of LBRY\"",
        "ups": 3
    },
    {
        "title": "Choosing quantity while playing a video!",
        "ups": 3
    },
    {
        "title": "Couldn\u2019t we figure out a way to pay content producers for producing content?",
        "ups": 2
    },
    {
        "title": "Upcoming Event: Android App Alpha Release - June 1, 2018 [Possible Date]",
        "ups": 3
    },
    {
        "title": "Some questions",
        "ups": 3
    },
    {
        "title": "Lbry Overview",
        "ups": 2
    },
    {
        "title": "All Spee.ch video's are down now..?",
        "ups": 3
    },
    {
        "title": "Beta Reward",
        "ups": 3
    },
    {
        "title": "Congrats to Video Chef And Other Contest Winners! See you at the LBRY...",
        "ups": 4
    },
    {
        "title": "Too Soon? bye bye JT",
        "ups": 3
    }
]