[
    {
        "title": "Why is this not listed on other exchanges?",
        "ups": 7
    },
    {
        "title": "Insurex been going crazy these past few days.",
        "ups": 8
    },
    {
        "title": "Any updates?",
        "ups": 4
    },
    {
        "title": "Insurex added to Blockfolio!",
        "ups": 5
    },
    {
        "title": "IXT Token Distribution \u2013 Insurex Team",
        "ups": 5
    },
    {
        "title": "Any updates since the ICO?",
        "ups": 4
    },
    {
        "title": "Partnership with fidentiaX",
        "ups": 5
    },
    {
        "title": "IXT Wallet",
        "ups": 4
    },
    {
        "title": "So why the fuck does it drop down back to 21m?",
        "ups": 4
    },
    {
        "title": "IXT token deposits and withdrawals are open on HitBTC",
        "ups": 3
    },
    {
        "title": "InsureX Whitepaper",
        "ups": 4
    },
    {
        "title": "Why are we up 88%?",
        "ups": 3
    },
    {
        "title": "\ud83d\ude80 iXledger up +25%! Any news?",
        "ups": 3
    },
    {
        "title": "Congrats to IXledger on the two new hires and Genre relationship",
        "ups": 3
    },
    {
        "title": "InsureX renamed to iXledger",
        "ups": 3
    },
    {
        "title": "Update from InsureX (July 17, 2017)",
        "ups": 3
    },
    {
        "title": "InsureX Q&amp;A at CryptoFizz.com",
        "ups": 3
    },
    {
        "title": "WOW! 24923.32 ETH Raised in 1 Hour!",
        "ups": 3
    },
    {
        "title": "How many tokens were sold in the presale and for what price ?",
        "ups": 3
    },
    {
        "title": "Follow us on Twitter!",
        "ups": 3
    },
    {
        "title": "Let the FOMO hit! Join the InsureX - Crowdsale 11th July \u2013 31st July",
        "ups": 3
    },
    {
        "title": "Welcome to the InsureX pre-sale!",
        "ups": 3
    },
    {
        "title": "INSUREX, the next big thing!",
        "ups": 3
    },
    {
        "title": "Workers\u2019 Compensation: Should You Self-Insure Your Company",
        "ups": 2
    },
    {
        "title": "No activity on Reddit?",
        "ups": 2
    }
]