[
    {
        "title": "Cryptocurrency Pioneer Charles Hoskinson Joins StormX as Senior Advisor",
        "ups": 31
    },
    {
        "title": "STORM Token Listed on Radar Relay \u2013 StormToken",
        "ups": 29
    },
    {
        "title": "TNW names Storm Play as the #1 way to earn free cryptocurrency",
        "ups": 26
    },
    {
        "title": "Storm on a Roll: back to top 100",
        "ups": 22
    },
    {
        "title": "My take on STORM's future",
        "ups": 24
    },
    {
        "title": "STORM Token AMA---February 21st! Comment With Your Questions",
        "ups": 15
    },
    {
        "title": "Subreddit is dead?",
        "ups": 16
    },
    {
        "title": "STORM breaks top 100 Market Cap!",
        "ups": 17
    },
    {
        "title": "StormToken group started on Facebook; *UP VOTE PLZ* then Join Us in building community!",
        "ups": 15
    },
    {
        "title": "Storm can now be used to get discounts on first class airline tickets!!",
        "ups": 16
    },
    {
        "title": "STORM Token to be listed on Coinnest",
        "ups": 15
    },
    {
        "title": "PETITION TO CHANGE BACKGROUND TO SOMETHING THAT CAN MAKE TEXT EASIER TO READ",
        "ups": 17
    },
    {
        "title": "Investing in Storm in 2018",
        "ups": 16
    },
    {
        "title": "New logo for Storm",
        "ups": 16
    },
    {
        "title": "STORM token is so promising.",
        "ups": 15
    },
    {
        "title": "Where can i get this coin?",
        "ups": 13
    },
    {
        "title": "STORM Token Listed on Popular Korean Exchange, Coinrail",
        "ups": 13
    },
    {
        "title": "STORM is now listed on Moonstats \ud83d\ude80 Latest rates, live &amp; historical charts and calculator.",
        "ups": 11
    },
    {
        "title": "My Biggest STORM Coin regret.",
        "ups": 13
    },
    {
        "title": "Putting all my chips on $STORM. If today taught us anything, it\u2019s that coins with real value, and a real solution will survive and thrive.",
        "ups": 12
    },
    {
        "title": "I mentioned STORM in my video :D",
        "ups": 12
    },
    {
        "title": "/r/cryptophile: Coins in top 100 whose price jumped by more than 50% in last 12 hours! - WAX, Medibloc, Storm",
        "ups": 13
    },
    {
        "title": "The date all the token sale people got in can sell?",
        "ups": 12
    },
    {
        "title": "STORM Token Listed on HitBTC",
        "ups": 12
    },
    {
        "title": "Best project ever!",
        "ups": 11
    }
]